inspectus/__init__.py
inspectus/attention_viz.py
inspectus/binned_heatmap_viz.py
inspectus/distribution_viz.py
inspectus/histogram_viz.py
inspectus/scatter_viz.py
inspectus/token_viz.py
inspectus/utils.py
inspectus/data_logger/__init__.py
inspectus/static/css/charts.css
inspectus/static/js/charts.js
inspectus-0.2.0.dist-info/METADATA
inspectus-0.2.0.dist-info/WHEEL
inspectus-0.2.0.dist-info/top_level.txt
inspectus-0.2.0.dist-info/RECORD
