Metadata-Version: 2.1
Name: inspectus
Version: 0.2.0
Summary: Analytics for LLMs
Home-page: https://github.com/labmlai/inspectus
Author: labml.ai
Author-email: contact@labml.ai
Project-URL: Documentation, https://docs.labml.ai/
Keywords: llm
Classifier: Programming Language :: Python :: 3
Classifier: License :: OSI Approved :: MIT License
Classifier: Intended Audience :: Developers
Classifier: Intended Audience :: Science/Research
Classifier: Topic :: Scientific/Engineering
Classifier: Topic :: Scientific/Engineering :: Mathematics
Classifier: Topic :: Scientific/Engineering :: Artificial Intelligence
Classifier: Topic :: Software Development
Classifier: Topic :: Software Development :: Libraries
Classifier: Topic :: Software Development :: Libraries :: Python Modules
Requires-Dist: labml (>=0.5.2)
Requires-Dist: altair (>=5.3.0)
